fix_mult.v
module fix_mult #(
    parameter WIDTHa = 16,
    parameter WIDTHb = 16,
    parameter WIDTHr = 16 
)(
    input clk,
    input rstn,
    input vld_in,           //vld_in和a,b同时进来，持续一个周期后为0     
    input [WIDTHa-1:0] a,    // 二进制定点补码 
    input [WIDTHb-1:0] b,    // 二进制定点补码 
    output [WIDTHr-1:0] r,   //r 与vld_out 同时有效这样有利于vld_out作为下一级的vld_in
    output vld_out
);

reg signed [WIDTHa-1:0] a_reg;reg signed [WIDTHb-1:0]b_reg;
reg signed [WIDTHr-1:0] result_reg;
reg [WIDTHa+WIDTHb-1:0] r_reg;

always @(posedge clk or negedge rstn) begin
    if (!rstn) begin
        a_reg <= 0;
        b_reg <= 0;
    end else if (vld_in) begin
        a_reg <=a;
        b_reg <=b;
    end
end

reg vld_in_diff;
reg finish_mult;

always @(posedge clk) begin
    vld_in_diff <= vld_in;
end


always @( *) begin
if(!rstn)
    begin
      r_reg=0;
      finish_mult=0;
    end
else if (vld_in_diff) begin 
    r_reg=a_reg*b_reg;
    finish_mult=1;
end
else begin
  r_reg=0;finish_mult=0;
end    
end

reg vld_out_reg;

always @(*) begin
    if(!rstn)   
        begin
           result_reg=0;  
           vld_out_reg=0;                                                                                                                                              
        end
    else if(finish_mult==1)
        begin
          result_reg=r_reg[WIDTHa+WIDTHb-3:WIDTHa+WIDTHb-WIDTHr-2];
          vld_out_reg=1;
        end
    else begin
        result_reg=0;
        vld_out_reg=0;
    end 

end

assign vld_out=vld_out_reg;
assign r=result_reg;
endmodule

fix_mult_tb.v
`include "fix_mult.v"
module fix_mult_tb();
    reg clk, rstn, vld_in;
    reg signed  [WIDTHa-1:0] a; 
    reg signed  [WIDTHb-1:0] b;
    wire signed [WIDTHr-1:0] r;
    wire vld_out;

    parameter WIDTHa = 16; //q9.7
    parameter WIDTHb = 16;//cos sin值q 2.14
    parameter WIDTHr = 16;//q11.5

    // 实例化 fix_mult 模块，使用正确的参数名
    fix_mult #(.WIDTHa(WIDTHa), .WIDTHb(WIDTHb), .WIDTHr(WIDTHr)) fix_mult_u1N (
        .clk(clk),
        .rstn(rstn),
        .vld_in(vld_in),
        .vld_out(vld_out),
        .a(a),
        .b(b),
        .r(r)
    );

    parameter T = 10;

    // 时钟生成
    always #(T/2) clk = ~clk;
    reg [WIDTHa-1:0] a_mem[0:511];
    reg [WIDTHb-1:0] b_mem[0:511];
    reg [WIDTHr-1:0] r_mem[0:511];

    integer i=0;
    integer file_r;
    initial begin
        clk = 1; rstn = 0; vld_in = 0;a=0;b=0;i=0;
        $readmemb("C:\\Users\\32172\\Desktop\\fft_fix\\scr\\valid\\a_fix_bin.txt", a_mem);
        $readmemb("C:\\Users\\32172\\Desktop\\fft_fix\\scr\\valid\\b_fix_bin.txt", b_mem);
        file_r=$fopen("C:\\Users\\32172\\Desktop\\fft_fix\\scr\\valid\\r_fix_bin.txt", "w");
        #(T + 1) rstn = 1; 
        #(T - 1) ;
        repeat(512)
            begin
                a=a_mem[i];
                b=b_mem[i];
                vld_in=1;
                #(T);
                vld_in=0;
                if(vld_out)
                    $fdisplay(file_r,"%b",r);
                #(T);
                i=i+1;
            end
        $fclose(file_r);
        $finish;
    end
initial begin
   $dumpfile("fix_mult_tb.vcd"); //生成的vcd文件名称
   $dumpvars(0, fix_mult_tb); //tb模块名称
end
endmodule

fix_mult_tb.vcd
$date
	Thu Feb 13 17:11:52 2025
$end
$version
	Icarus Verilog
$end
$timescale
	1s
$end
$scope module fix_mult_tb $end
$var wire 1 ! vld_out $end
$var wire 16 " r [15:0] $end
$var reg 16 # a [15:0] $end
$var reg 16 $ b [15:0] $end
$var reg 1 % clk $end
$var reg 1 & rstn $end
$var reg 1 ' vld_in $end
$var integer 32 ( file_r [31:0] $end
$var integer 32 ) i [31:0] $end
$scope module fix_mult_u1N $end
$var wire 16 * a [15:0] $end
$var wire 16 + b [15:0] $end
$var wire 1 % clk $end
$var wire 16 , r [15:0] $end
$var wire 1 & rstn $end
$var wire 1 ' vld_in $end
$var wire 1 ! vld_out $end
$var reg 16 - a_reg [15:0] $end
$var reg 16 . b_reg [15:0] $end
$var reg 1 / finish_mult $end
$var reg 32 0 r_reg [31:0] $end
$var reg 16 1 result_reg [15:0] $end
$var reg 1 2 vld_in_diff $end
$var reg 1 3 vld_out_reg $end
$upscope $end
$upscope $end
$enddefinitions $end
#0
$dumpvars
03
02
b0 1
b0 0
0/
b0 .
b0 -
b0 ,
b0 +
b0 *
b0 )
b10000000000000000000000000000011 (
0'
0&
1%
b0 $
b0 #
b0 "
0!
$end
#5
0%
#10
1%
#11
1&
#15
0%
#20
1!
13
b1110101001001011 "
b1110101001001011 ,
b1110101001001011 1
1/
b11111010100100101100101001100111 0
12
b1111001110001111 .
b110111110101001 -
1%
1'
b1111001110001111 $
b1111001110001111 +
b110111110101001 #
b110111110101001 *
#25
0%
#30
0!
03
b0 "
b0 ,
b0 1
0/
b0 0
02
1%
0'
#35
0%
#40
1!
13
b100111100011100 "
b100111100011100 ,
b100111100011100 1
1/
b10011110001110011011000111101 0
12
b1101001110110111 .
b1000110110101011 -
1%
1'
b1101001110110111 $
b1101001110110111 +
b1000110110101011 #
b1000110110101011 *
b1 )
#45
0%
#50
0!
03
b0 "
b0 ,
b0 1
0/
b0 0
02
1%
0'
#55
0%
#60
1!
13
b1000000111001 "
b1000000111001 ,
b1000000111001 1
1/
b100000011100101011110101001 0
12
b1010000000011 .
b11001111100011 -
1%
1'
b1010000000011 $
b1010000000011 +
b11001111100011 #
b11001111100011 *
b10 )
#65
0%
#70
0!
03
b0 "
b0 ,
b0 1
0/
b0 0
02
1%
0'
#75
0%
#80
1!
13
b1110111010101 "
b1110111010101 ,
b1110111010101 1
1/
b111011101010101110110111100 0
12
b1100110101010 .
b100101001100110 -
1%
1'
b1100110101010 $
b1100110101010 +
b100101001100110 #
b100101001100110 *
b11 )
#85
0%
#90
0!
03
b0 "
b0 ,
b0 1
0/
b0 0
02
1%
0'
#95
0%
#100
1!
13
b100100010110011 "
b100100010110011 ,
b100100010110011 1
1/
b10010001011001111100111010000 0
12
b10100010100110 .
b111001001111000 -
1%
1'
b10100010100110 $
b10100010100110 +
b111001001111000 #
b111001001111000 *
b100 )
#105
0%
#110
0!
03
b0 "
b0 ,
b0 1
0/
b0 0
02
1%
0'
#115
0%
#120
1!
13
b100111000101001 "
b100111000101001 ,
b100111000101001 1
1/
b10011100010100110001010001100 0
12
b1101011011101100 .
b1000011000111001 -
1%
1'
b1101011011101100 $
b1101011011101100 +
b1000011000111001 #
b1000011000111001 *
b101 )
#125
0%
#130
0!
03
b0 "
b0 ,
b0 1
0/
b0 0
02
1%
0'
#135
0%
#140
1!
13
b1111111101110010 "
b1111111101110010 ,
b1111111101110010 1
1/
b11111111110111001001110100010100 0
12
b11011010 .
b1101011001110010 -
1%
1'
b11011010 $
b11011010 +
b1101011001110010 #
b1101011001110010 *
b110 )
#145
0%
#150
0!
03
b0 "
b0 ,
b0 1
0/
b0 0
02
1%
0'
#155
0%
#160
1!
13
b1111101111110011 "
b1111101111110011 ,
b1111101111110011 1
1/
b11111110111111001101001001011111 0
12
b1111110000010011 .
b100001000000101 -
1%
1'
b1111110000010011 $
b1111110000010011 +
b100001000000101 #
b100001000000101 *
b111 )
#165
0%
#170
0!
03
b0 "
b0 ,
b0 1
0/
b0 0
02
1%
0'
#175
0%
#180
1!
13
b1011100010101100 "
b1011100010101100 ,
b1011100010101100 1
1/
b11101110001010110010110001100000 0
12
b1100010110000110 .
b100111000010000 -
1%
1'
b1100010110000110 $
b1100010110000110 +
b100111000010000 #
b100111000010000 *
b1000 )
#185
0%
#190
0!
03
b0 "
b0 ,
b0 1
0/
b0 0
02
1%
0'
#195
0%
#200
1!
13
b1111110111100111 "
b1111110111100111 ,
b1111110111100111 1
1/
b11111111011110011100010000100101 0
12
b101110010011 .
b1111010001100111 -
1%
1'
b101110010011 $
b101110010011 +
b1111010001100111 #
b1111010001100111 *
b1001 )
#205
0%
#210
0!
03
b0 "
b0 ,
b0 1
0/
b0 0
02
1%
0'
#215
0%
#220
1!
13
b10100010001101 "
b10100010001101 ,
b10100010001101 1
1/
b1010001000110101011001011011 0
12
b1101010101001111 .
b1100001100110101 -
1%
1'
b1101010101001111 $
b1101010101001111 +
b1100001100110101 #
b1100001100110101 *
b1010 )
#225
0%
#230
0!
03
b0 "
b0 ,
b0 1
0/
b0 0
02
1%
0'
#235
0%
#240
1!
13
b1101001000100010 "
b1101001000100010 ,
b1101001000100010 1
1/
b11110100100010001001001100010111 0
12
b1100111011001 .
b1000111001101111 -
1%
1'
b1100111011001 $
b1100111011001 +
b1000111001101111 #
b1000111001101111 *
b1011 )
#245
0%
#250
0!
03
b0 "
b0 ,
b0 1
0/
b0 0
02
1%
0'
#255
0%
#260
1!
13
b101011100010110 "
b101011100010110 ,
b101011100010110 1
1/
b10101110001011011100101110110 0
12
b11110110101011 .
b101101001100010 -
1%
1'
b11110110101011 $
b11110110101011 +
b101101001100010 #
b101101001100010 *
b1100 )
#265
0%
#270
0!
03
b0 "
b0 ,
b0 1
0/
b0 0
02
1%
0'
#275
0%
#280
1!
13
b1111111100101011 "
b1111111100101011 ,
b1111111100101011 1
1/
b11111111110010101111101111101110 0
12
b1111111101010001 .
b100110110001110 -
1%
1'
b1111111101010001 $
b1111111101010001 +
b100110110001110 #
b100110110001110 *
b1101 )
#285
0%
#290
0!
03
b0 "
b0 ,
b0 1
0/
b0 0
02
1%
0'
#295
0%
#300
1!
13
b1111110100111000 "
b1111110100111000 ,
b1111110100111000 1
1/
b11111111010011100011110110001100 0
12
b1110110100111110 .
b100101111010 -
1%
1'
b1110110100111110 $
b1110110100111110 +
b100101111010 #
b100101111010 *
b1110 )
#305
0%
#310
0!
03
b0 "
b0 ,
b0 1
0/
b0 0
02
1%
0'
#315
0%
#320
1!
13
b1010011101110001 "
b1010011101110001 ,
b1010011101110001 1
1/
b11101001110111000100100100111111 0
12
b11101011111101 .
b1001111111101011 -
1%
1'
b11101011111101 $
b11101011111101 +
b1001111111101011 #
b1001111111101011 *
b1111 )
#325
0%
#330
0!
03
b0 "
b0 ,
b0 1
0/
b0 0
02
1%
0'
#335
0%
#340
1!
13
b1111001110001101 "
b1111001110001101 ,
b1111001110001101 1
1/
b11111100111000110100011010001000 0
12
b10001001101110 .
b1110100011011100 -
1%
1'
b10001001101110 $
b10001001101110 +
b1110100011011100 #
b1110100011011100 *
b10000 )
#345
0%
#350
0!
03
b0 "
b0 ,
b0 1
0/
b0 0
02
1%
0'
#355
0%
#360
1!
13
b1000010100111 "
b1000010100111 ,
b1000010100111 1
1/
b100001010011110001010000111 0
12
b10110101100101 .
b1011101111011 -
1%
1'
b10110101100101 $
b10110101100101 +
b1011101111011 #
b1011101111011 *
b10001 )
#365
0%
#370
0!
03
b0 "
b0 ,
b0 1
0/
b0 0
02
1%
0'
#375
0%
#380
1!
13
b1101001010000 "
b1101001010000 ,
b1101001010000 1
1/
b110100101000000100100011000 0
12
b1111000010011000 .
b1001001010110001 -
1%
1'
b1111000010011000 $
b1111000010011000 +
b1001001010110001 #
b1001001010110001 *
b10010 )
#385
0%
#390
0!
03
b0 "
b0 ,
b0 1
0/
b0 0
02
1%
0'
#395
0%
#400
1!
13
b10010111001010 "
b10010111001010 ,
b10010111001010 1
1/
b1001011100101010101000110111 0
12
b11001000001101 .
b11000001010011 -
1%
1'
b11001000001101 $
b11001000001101 +
b11000001010011 #
b11000001010011 *
b10011 )
#405
0%
#410
0!
03
b0 "
b0 ,
b0 1
0/
b0 0
02
1%
0'
#415
0%
#420
1!
13
b1100000011001000 "
b1100000011001000 ,
b1100000011001000 1
1/
b11110000001100100000111101101100 0
12
b11100111110001 .
b1011101000101100 -
1%
1'
b11100111110001 $
b11100111110001 +
b1011101000101100 #
b1011101000101100 *
b10100 )
#425
0%
#430
0!
03
b0 "
b0 ,
b0 1
0/
b0 0
02
1%
0'
#435
0%
#440
1!
13
b11101110100101 "
b11101110100101 ,
b11101110100101 1
1/
b1110111010010100001101110110 0
12
b1111010001010 .
b111110011111111 -
1%
1'
b1111010001010 $
b1111010001010 +
b111110011111111 #
b111110011111111 *
b10101 )
#445
0%
#450
0!
03
b0 "
b0 ,
b0 1
0/
b0 0
02
1%
0'
#455
0%
#460
1!
13
b1111100001011011 "
b1111100001011011 ,
b1111100001011011 1
1/
b11111110000101101100010011000000 0
12
b1110100010100000 .
b1010011101110 -
1%
1'
b1110100010100000 $
b1110100010100000 +
b1010011101110 #
b1010011101110 *
b10110 )
#465
0%
#470
0!
03
b0 "
b0 ,
b0 1
0/
b0 0
02
1%
0'
#475
0%
#480
1!
13
b1110001101111100 "
b1110001101111100 ,
b1110001101111100 1
1/
b11111000110111110010001011111100 0
12
b1100011100010010 .
b10000000001110 -
1%
1'
b1100011100010010 $
b1100011100010010 +
b10000000001110 #
b10000000001110 *
b10111 )
#485
0%
#490
0!
03
b0 "
b0 ,
b0 1
0/
b0 0
02
1%
0'
#495
0%
#500
1!
13
b1101010010000001 "
b1101010010000001 ,
b1101010010000001 1
1/
b11110101001000000100000100010000 0
12
b1100011011010011 .
b11000010110000 -
1%
1'
b1100011011010011 $
b1100011011010011 +
b11000010110000 #
b11000010110000 *
b11000 )
#505
0%
#510
0!
03
b0 "
b0 ,
b0 1
0/
b0 0
02
1%
0'
#515
0%
#520
1!
13
b1011111101 "
b1011111101 ,
b1011111101 1
1/
b101111110111000111001100 0
12
b1110101011010010 .
b1111011011110110 -
1%
1'
b1110101011010010 $
b1110101011010010 +
b1111011011110110 #
b1111011011110110 *
b11001 )
#525
0%
#530
0!
03
b0 "
b0 ,
b0 1
0/
b0 0
02
1%
0'
#535
0%
#540
1!
13
b1111111011111111 "
b1111111011111111 ,
b1111111011111111 1
1/
b11111111101111111110011011110111 0
12
b1110010001 .
b1110111000000111 -
1%
1'
b1110010001 $
b1110010001 +
b1110111000000111 #
b1110111000000111 *
b11010 )
#545
0%
#550
0!
03
b0 "
b0 ,
b0 1
0/
b0 0
02
1%
0'
#555
0%
#560
1!
13
b1100011010001110 "
b1100011010001110 ,
b1100011010001110 1
1/
b11110001101000111000110111100001 0
12
b1100011000110011 .
b11111110011011 -
1%
1'
b1100011000110011 $
b1100011000110011 +
b11111110011011 #
b11111110011011 *
b11011 )
#565
0%
#570
0!
03
b0 "
b0 ,
b0 1
0/
b0 0
02
1%
0'
#575
0%
#580
1!
13
b1111001111111000 "
b1111001111111000 ,
b1111001111111000 1
1/
b11111100111111100001010110000100 0
12
b111000010001 .
b1100100101000100 -
1%
1'
b111000010001 $
b111000010001 +
b1100100101000100 #
b1100100101000100 *
b11100 )
#585
0%
#590
0!
03
b0 "
b0 ,
b0 1
0/
b0 0
02
1%
0'
#595
0%
#600
1!
13
b1111111101000101 "
b1111111101000101 ,
b1111111101000101 1
1/
b11111111110100010110100010110100 0
12
b11010110111010 .
b1111111100100010 -
1%
1'
b11010110111010 $
b11010110111010 +
b1111111100100010 #
b1111111100100010 *
b11101 )
#605
0%
#610
0!
03
b0 "
b0 ,
b0 1
0/
b0 0
02
1%
0'
#615
0%
#620
1!
13
b1110101111010110 "
b1110101111010110 ,
b1110101111010110 1
1/
b11111010111101011010100000110100 0
12
b1100101001101001 .
b1100000010100 -
1%
1'
b1100101001101001 $
b1100101001101001 +
b1100000010100 #
b1100000010100 *
b11110 )
#625
0%
#630
0!
03
b0 "
b0 ,
b0 1
0/
b0 0
02
1%
0'
#635
0%
#640
1!
13
b1110001101101010 "
b1110001101101010 ,
b1110001101101010 1
1/
b11111000110110101011110001001100 0
12
b1100101010100 .
b1011011111000111 -
1%
1'
b1100101010100 $
b1100101010100 +
b1011011111000111 #
b1011011111000111 *
b11111 )
#645
0%
#650
0!
03
b0 "
b0 ,
b0 1
0/
b0 0
02
1%
0'
#655
0%
#660
1!
13
b1100010011101101 "
b1100010011101101 ,
b1100010011101101 1
1/
b11110001001110110110000111011100 0
12
b1100010010011010 .
b11111110100110 -
1%
1'
b1100010010011010 $
b1100010010011010 +
b11111110100110 #
b11111110100110 *
b100000 )
#665
0%
#670
0!
03
b0 "
b0 ,
b0 1
0/
b0 0
02
1%
0'
#675
0%
#680
1!
13
b1100111000010 "
b1100111000010 ,
b1100111000010 1
1/
b110011100001001111001101000 0
12
b1100010001000001 .
b1110010001101000 -
1%
1'
b1100010001000001 $
b1100010001000001 +
b1110010001101000 #
b1110010001101000 *
b100001 )
#685
0%
#690
0!
03
b0 "
b0 ,
b0 1
0/
b0 0
02
1%
0'
#695
0%
#700
1!
13
b1100100010110101 "
b1100100010110101 ,
b1100100010110101 1
1/
b11110010001011010111000001001100 0
12
b1100000101000010 .
b11100001100110 -
1%
1'
b1100000101000010 $
b1100000101000010 +
b11100001100110 #
b11100001100110 *
b100010 )
#705
0%
#710
0!
03
b0 "
b0 ,
b0 1
0/
b0 0
02
1%
0'
#715
0%
#720
1!
13
b1111100000100001 "
b1111100000100001 ,
b1111100000100001 1
1/
b11111110000010000110100001110111 0
12
b1110111011011101 .
b1110101100011 -
1%
1'
b1110111011011101 $
b1110111011011101 +
b1110101100011 #
b1110101100011 *
b100011 )
#725
0%
#730
0!
03
b0 "
b0 ,
b0 1
0/
b0 0
02
1%
0'
#735
0%
#740
1!
13
b11110011110110 "
b11110011110110 ,
b11110011110110 1
1/
b1111001111011001000001101001 0
12
b1101110001011001 .
b1001001010010001 -
1%
1'
b1101110001011001 $
b1101110001011001 +
b1001001010010001 #
b1001001010010001 *
b100100 )
#745
0%
#750
0!
03
b0 "
b0 ,
b0 1
0/
b0 0
02
1%
0'
#755
0%
#760
1!
13
b1111101011000110 "
b1111101011000110 ,
b1111101011000110 1
1/
b11111110101100011000011101011111 0
12
b1111110100100001 .
b111010001111111 -
1%
1'
b1111110100100001 $
b1111110100100001 +
b111010001111111 #
b111010001111111 *
b100101 )
#765
0%
#770
0!
03
b0 "
b0 ,
b0 1
0/
b0 0
02
1%
0'
#775
0%
#780
1!
13
b1110111101001011 "
b1110111101001011 ,
b1110111101001011 1
1/
b11111011110100101110101010101100 0
12
b100001110111 .
b1000000110110100 -
1%
1'
b100001110111 $
b100001110111 +
b1000000110110100 #
b1000000110110100 *
b100110 )
#785
0%
#790
0!
03
b0 "
b0 ,
b0 1
0/
b0 0
02
1%
0'
#795
0%
#800
1!
13
b1111011010001110 "
b1111011010001110 ,
b1111011010001110 1
1/
b11111101101000111001001111001000 0
12
b1010010111011 .
b1110001011011000 -
1%
1'
b1010010111011 $
b1010010111011 +
b1110001011011000 #
b1110001011011000 *
b100111 )
#805
0%
#810
0!
03
b0 "
b0 ,
b0 1
0/
b0 0
02
1%
0'
#815
0%
#820
1!
13
b1100000101010110 "
b1100000101010110 ,
b1100000101010110 1
1/
b11110000010101011001100010010100 0
12
b11011111011010 .
b1011100000110010 -
1%
1'
b11011111011010 $
b11011111011010 +
b1011100000110010 #
b1011100000110010 *
b101000 )
#825
0%
#830
0!
03
b0 "
b0 ,
b0 1
0/
b0 0
02
1%
0'
#835
0%
#840
1!
13
b10010010110110 "
b10010010110110 ,
b10010010110110 1
1/
b1001001011011010000010100001 0
12
b1100110100101101 .
b1101000111000101 -
1%
1'
b1100110100101101 $
b1100110100101101 +
b1101000111000101 #
b1101000111000101 *
b101001 )
#845
0%
#850
0!
03
b0 "
b0 ,
b0 1
0/
b0 0
02
1%
0'
#855
0%
#860
1!
13
b1111111100011100 "
b1111111100011100 ,
b1111111100011100 1
1/
b11111111110001110000110001010000 0
12
b11101011001010 .
b1111111100001000 -
1%
1'
b11101011001010 $
b11101011001010 +
b1111111100001000 #
b1111111100001000 *
b101010 )
#865
0%
#870
0!
03
b0 "
b0 ,
b0 1
0/
b0 0
02
1%
0'
#875
0%
#880
1!
13
b11101111001001 "
b11101111001001 ,
b11101111001001 1
1/
b1110111100100110010011100011 0
12
b10011101110111 .
b110000011110101 -
1%
1'
b10011101110111 $
b10011101110111 +
b110000011110101 #
b110000011110101 *
b101011 )
#885
0%
#890
0!
03
b0 "
b0 ,
b0 1
0/
b0 0
02
1%
0'
#895
0%
#900
1!
13
b1111110001001110 "
b1111110001001110 ,
b1111110001001110 1
1/
b11111111000100111001001100010010 0
12
b1111011011000001 .
b1100110010010 -
1%
1'
b1111011011000001 $
b1111011011000001 +
b1100110010010 #
b1100110010010 *
b101100 )
#905
0%
#910
0!
03
b0 "
b0 ,
b0 1
0/
b0 0
02
1%
0'
#915
0%
#920
1!
13
b1000110010010 "
b1000110010010 ,
b1000110010010 1
1/
b100011001001011010001000110 0
12
b1101011010111101 .
b1110010010111110 -
1%
1'
b1101011010111101 $
b1101011010111101 +
b1110010010111110 #
b1110010010111110 *
b101101 )
#925
0%
#930
0!
03
b0 "
b0 ,
b0 1
0/
b0 0
02
1%
0'
#935
0%
#940
1!
13
b1111110100011111 "
b1111110100011111 ,
b1111110100011111 1
1/
b11111111010001111110111111111100 0
12
b1101000000110110 .
b1111011010 -
1%
1'
b1101000000110110 $
b1101000000110110 +
b1111011010 #
b1111011010 *
b101110 )
#945
0%
#950
0!
03
b0 "
b0 ,
b0 1
0/
b0 0
02
1%
0'
#955
0%
#960
1!
13
b1101010100001 "
b1101010100001 ,
b1101010100001 1
1/
b110101010000110111000010110 0
12
b1000010101011 .
b110011001000010 -
1%
1'
b1000010101011 $
b1000010101011 +
b110011001000010 #
b110011001000010 *
b101111 )
#965
0%
#970
0!
03
b0 "
b0 ,
b0 1
0/
b0 0
02
1%
0'
#975
0%
#980
1!
13
b10101001010 "
b10101001010 ,
b10101001010 1
1/
b1010100101001111010001101 0
12
b10110001101 .
b11110100000001 -
1%
1'
b10110001101 $
b10110001101 +
b11110100000001 #
b11110100000001 *
b110000 )
#985
0%
#990
0!
03
b0 "
b0 ,
b0 1
0/
b0 0
02
1%
0'
#995
0%
#1000
1!
13
b10001101110 "
b10001101110 ,
b10001101110 1
1/
b1000110111010000111110110 0
12
b10100101011 .
b11011011100010 -
1%
1'
b10100101011 $
b10100101011 +
b11011011100010 #
b11011011100010 *
b110001 )
#1005
0%
#1010
0!
03
b0 "
b0 ,
b0 1
0/
b0 0
02
1%
0'
#1015
0%
#1020
1!
13
b1100011111111 "
b1100011111111 ,
b1100011111111 1
1/
b110001111111100011001111011 0
12
b1011100100101 .
b100010100011111 -
1%
1'
b1011100100101 $
b1011100100101 +
b100010100011111 #
b100010100011111 *
b110010 )
#1025
0%
#1030
0!
03
b0 "
b0 ,
b0 1
0/
b0 0
02
1%
0'
#1035
0%
#1040
1!
13
b1100111010000010 "
b1100111010000010 ,
b1100111010000010 1
1/
b11110011101000001010010110010011 0
12
b1111101110001 .
b1001101101000011 -
1%
1'
b1111101110001 $
b1111101110001 +
b1001101101000011 #
b1001101101000011 *
b110011 )
#1045
0%
#1050
0!
03
b0 "
b0 ,
b0 1
0/
b0 0
02
1%
0'
#1055
0%
#1060
1!
13
b11001101101000 "
b11001101101000 ,
b11001101101000 1
1/
b1100110110100001001110000100 0
12
b1110000010100 .
b111010100101101 -
1%
1'
b1110000010100 $
b1110000010100 +
b111010100101101 #
b111010100101101 *
b110100 )
#1065
0%
#1070
0!
03
b0 "
b0 ,
b0 1
0/
b0 0
02
1%
0'
#1075
0%
#1080
1!
13
b10110001001 "
b10110001001 ,
b10110001001 1
1/
b1011000100110101110000001 0
12
b10101101001111 .
b100000101111 -
1%
1'
b10101101001111 $
b10101101001111 +
b100000101111 #
b100000101111 *
b110101 )
#1085
0%
#1090
0!
03
b0 "
b0 ,
b0 1
0/
b0 0
02
1%
0'
#1095
0%
#1100
1!
13
b1101000101111110 "
b1101000101111110 ,
b1101000101111110 1
1/
b11110100010111111010001010111000 0
12
b1101101111101110 .
b101001010000100 -
1%
1'
b1101101111101110 $
b1101101111101110 +
b101001010000100 #
b101001010000100 *
b110110 )
#1105
0%
#1110
0!
03
b0 "
b0 ,
b0 1
0/
b0 0
02
1%
0'
#1115
0%
#1120
1!
13
b1111111000001101 "
b1111111000001101 ,
b1111111000001101 1
1/
b11111111100000110111011001100100 0
12
b111111111 .
b1100000110011100 -
1%
1'
b111111111 $
b111111111 +
b1100000110011100 #
b1100000110011100 *
b110111 )
#1125
0%
#1130
0!
03
b0 "
b0 ,
b0 1
0/
b0 0
02
1%
0'
#1135
0%
#1140
1!
13
b10110111 "
b10110111 ,
b10110111 1
1/
b1011011101100011111000 0
12
b1111111010100110 .
b1101111000010100 -
1%
1'
b1111111010100110 $
b1111111010100110 +
b1101111000010100 #
b1101111000010100 *
b111000 )
#1145
0%
#1150
0!
03
b0 "
b0 ,
b0 1
0/
b0 0
02
1%
0'
#1155
0%
#1160
1!
13
b1110111001000 "
b1110111001000 ,
b1110111001000 1
1/
b111011100100000110110010001 0
12
b10101000110011 .
b10110100101011 -
1%
1'
b10101000110011 $
b10101000110011 +
b10110100101011 #
b10110100101011 *
b111001 )
#1165
0%
#1170
0!
03
b0 "
b0 ,
b0 1
0/
b0 0
02
1%
0'
#1175
0%
#1180
1!
13
b1111011011010111 "
b1111011011010111 ,
b1111011011010111 1
1/
b11111101101101011111100001010100 0
12
b1010011101011 .
b1110001111111100 -
1%
1'
b1010011101011 $
b1010011101011 +
b1110001111111100 #
b1110001111111100 *
b111010 )
#1185
0%
#1190
0!
03
b0 "
b0 ,
b0 1
0/
b0 0
02
1%
0'
#1195
0%
#1200
1!
13
b1011111100100101 "
b1011111100100101 ,
b1011111100100101 1
1/
b11101111110010010101111101010100 0
12
b10010011100100 .
b1000111101111101 -
1%
1'
b10010011100100 $
b10010011100100 +
b1000111101111101 #
b1000111101111101 *
b111011 )
#1205
0%
#1210
0!
03
b0 "
b0 ,
b0 1
0/
b0 0
02
1%
0'
#1215
0%
#1220
1!
13
b100011011101111 "
b100011011101111 ,
b100011011101111 1
1/
b10001101110111101101110001010 0
12
b1101100001101010 .
b1000110101010001 -
1%
1'
b1101100001101010 $
b1101100001101010 +
b1000110101010001 #
b1000110101010001 *
b111100 )
#1225
0%
#1230
0!
03
b0 "
b0 ,
b0 1
0/
b0 0
02
1%
0'
#1235
0%
#1240
1!
13
b1011101010011110 "
b1011101010011110 ,
b1011101010011110 1
1/
b11101110101001111010001101110100 0
12
b1100100010110010 .
b101000001001010 -
1%
1'
b1100100010110010 $
b1100100010110010 +
b101000001001010 #
b101000001001010 *
b111101 )
#1245
0%
#1250
0!
03
b0 "
b0 ,
b0 1
0/
b0 0
02
1%
0'
#1255
0%
#1260
1!
13
b1111111100111010 "
b1111111100111010 ,
b1111111100111010 1
1/
b11111111110011101010101001101110 0
12
b1110101011111 .
b1111111001010010 -
1%
1'
b1110101011111 $
b1110101011111 +
b1111111001010010 #
b1111111001010010 *
b111110 )
#1265
0%
#1270
0!
03
b0 "
b0 ,
b0 1
0/
b0 0
02
1%
0'
#1275
0%
#1280
1!
13
b1010100010111010 "
b1010100010111010 ,
b1010100010111010 1
1/
b11101010001011101010011001011001 0
12
b1101001111010101 .
b111111001110101 -
1%
1'
b1101001111010101 $
b1101001111010101 +
b111111001110101 #
b111111001110101 *
b111111 )
#1285
0%
#1290
0!
03
b0 "
b0 ,
b0 1
0/
b0 0
02
1%
0'
#1295
0%
#1300
1!
13
b1110101100111100 "
b1110101100111100 ,
b1110101100111100 1
1/
b11111010110011110001110101110001 0
12
b110110010111 .
b1001111000110111 -
1%
1'
b110110010111 $
b110110010111 +
b1001111000110111 #
b1001111000110111 *
b1000000 )
#1305
0%
#1310
0!
03
b0 "
b0 ,
b0 1
0/
b0 0
02
1%
0'
#1315
0%
#1320
1!
13
b11101001100 "
b11101001100 ,
b11101001100 1
1/
b1110100110011000110000010 0
12
b10011100001 .
b101111111000010 -
1%
1'
b10011100001 $
b10011100001 +
b101111111000010 #
b101111111000010 *
b1000001 )
#1325
0%
#1330
0!
03
b0 "
b0 ,
b0 1
0/
b0 0
02
1%
0'
#1335
0%
#1340
1!
13
b101000010011010 "
b101000010011010 ,
b101000010011010 1
1/
b10100001001101001111000111000 0
12
b1100100100100110 .
b1010000111110100 -
1%
1'
b1100100100100110 $
b1100100100100110 +
b1010000111110100 #
b1010000111110100 *
b1000010 )
#1345
0%
#1350
0!
03
b0 "
b0 ,
b0 1
0/
b0 0
02
1%
0'
#1355
0%
#1360
1!
13
b110110001110 "
b110110001110 ,
b110110001110 1
1/
b11011000111010100111000010 0
12
b1111001010110010 .
b1011111011001001 -
1%
1'
b1111001010110010 $
b1111001010110010 +
b1011111011001001 #
b1011111011001001 *
b1000011 )
#1365
0%
#1370
0!
03
b0 "
b0 ,
b0 1
0/
b0 0
02
1%
0'
#1375
0%
#1380
1!
13
b1110010010101010 "
b1110010010101010 ,
b1110010010101010 1
1/
b11111001001010101000010110010000 0
12
b1100101101011100 .
b10000100111100 -
1%
1'
b1100101101011100 $
b1100101101011100 +
b10000100111100 #
b10000100111100 *
b1000100 )
#1385
0%
#1390
0!
03
b0 "
b0 ,
b0 1
0/
b0 0
02
1%
0'
#1395
0%
#1400
1!
13
b110001010100011 "
b110001010100011 ,
b110001010100011 1
1/
b11000101010001100001001110110 0
12
b11100101101111 .
b110110111101010 -
1%
1'
b11100101101111 $
b11100101101111 +
b110110111101010 #
b110110111101010 *
b1000101 )
#1405
0%
#1410
0!
03
b0 "
b0 ,
b0 1
0/
b0 0
02
1%
0'
#1415
0%
#1420
1!
13
b1100101010110 "
b1100101010110 ,
b1100101010110 1
1/
b110010101011010000101100000 0
12
b11100000001010 .
b1110011110000 -
1%
1'
b11100000001010 $
b11100000001010 +
b1110011110000 #
b1110011110000 *
b1000110 )
#1425
0%
#1430
0!
03
b0 "
b0 ,
b0 1
0/
b0 0
02
1%
0'
#1435
0%
