fix_adder.v

module fix_adder #(
    parameter WIDTH1 = 9,//整数位
    parameter WIDTH2 = 7,//小数位
    parameter WIDTH = 16
)(
    input clk,
    input rstn,
    input vld_in,           //vld_in和a,b同时进来，持续一个周期后为0     
    input [WIDTH-1:0] a,    // 二进制定点补码
    input [WIDTH-1:0] b,    // 二进制定点补码 WIDTH1.WIDTH2
    output [WIDTH-1:0] r,   //r 与vld_out 同时有效这样有利于vld_out作为下一级的vld_in
    output vld_out,
    output overflow       // 溢出处理，直接舍弃将最高位仍然看出符号位，使得溢出的正数变成了负数
);

reg [WIDTH:0] a_reg, b_reg; 
reg [WIDTH:0]r_reg;
reg finish_add,vld_out_reg; 
reg a_sign,b_sign;

always @(posedge clk or negedge rstn) begin
    if (!rstn) begin
        a_reg <= 0;
        b_reg <= 0;
        a_sign<=0;
        b_sign<=0;
    end else if (vld_in) begin
        a_reg <= {a[WIDTH-1],a};
        b_reg <= {b[WIDTH-1],b};
        a_sign<=a[WIDTH-1];
        b_sign<=b[WIDTH-1];
    end
end

reg vld_in_diff;

always @(posedge clk) begin
    vld_in_diff <= vld_in;
end

reg [WIDTH:0] c;

integer i;
always @(*) begin
    if (!rstn) begin
        c = 0;
        r_reg = 0;
        finish_add = 0;
    end else if (vld_in_diff) begin
        for (i = 0; i < WIDTH+1; i = i + 1) begin
            if(i==0) 
            begin
                r_reg[i]=a_reg[i]^b_reg[i];
                c[i]=a_reg[i]&b_reg[i];
            end
              
            else
                begin 
                    r_reg[i] = a_reg[i] ^ b_reg[i] ^ c[i-1];
                    c[i]=(a_reg[i]&b_reg[i])|((a_reg[i]^b_reg[i])&c[i-1]);
                end
        end
        finish_add = 1;
    end 
    else begin
        c = 0;
        r_reg = 0;
        finish_add = 0;
    end
end

reg overflow_reg=0;
reg [WIDTH:0] result_reg;
 always @(*) begin
    if(!rstn)   
        begin
           result_reg=0; 
           overflow_reg=0;                                                                                                                                                     
        end
    else if(finish_add==1)
        begin
            vld_out_reg=1;
            if(!(a_sign^b_sign)&&r_reg[WIDTH]^r_reg[WIDTH-1])//只有同号时才会出现溢出，一正一负相加结果不会溢出
                overflow_reg=1;//溢出时就会舍弃高位,例如2^31-1加1后本来得到2^31,10000....00,31个0，但是溢出，抢占了符号位，但是系统仍将其看作符号位
                //所以最后系统认成是2^-32c次幂
            else 
                overflow_reg=0;
            result_reg=r_reg;    
        end
    else begin 
        overflow_reg=0;
        result_reg=0;
        vld_out_reg=0;
    end    
 end
// 输出寄存器赋值

assign overflow=overflow_reg;
assign vld_out=vld_out_reg;
assign r=result_reg[WIDTH-1:0];
endmodule

fix_adder_tb.v
`include "fix_adder.v"
module fix_adder_tb();
    reg clk, rstn, vld_in;
    reg signed  [WIDTH-1:0] a, b;
    wire signed [WIDTH-1:0] r;
    wire vld_out,overflow;

    parameter WIDTH1 =10;
    parameter WIDTH2 =6;
    parameter WIDTH = 16;

    // 实例化 fix_adder 模块，使用正确的参数名
    fix_adder #(.WIDTH(WIDTH), .WIDTH1(WIDTH1), .WIDTH2(WIDTH2)) fix_adder_u1N (
        .clk(clk),
        .rstn(rstn),
        .vld_in(vld_in),
        .vld_out(vld_out),
        .a(a),
        .b(b),
        .r(r),
        .overflow(overflow)
    );

    parameter T = 10;

    // 时钟生成
    always #(T/2) clk = ~clk;

    reg [WIDTH-1:0] a_mem[0:511];
    reg [WIDTH-1:0] b_mem[0:511];
    reg [WIDTH-1:0] r_mem[0:511];

    integer i=0;
    integer file_adder,file_sub;

    initial begin
        clk = 0; rstn = 0; vld_in = 0;a=0;b=0;
        $readmemb("C:\\Users\\32172\\Desktop\\fft_fix\\scr\\valid_adder\\a_fix_bin.txt", a_mem);
        $readmemb("C:\\Users\\32172\\Desktop\\fft_fix\\scr\\valid_adder\\b_fix_bin.txt", b_mem);
        file_adder=$fopen("C:\\Users\\32172\\Desktop\\fft_fix\\scr\\valid_adder\\adder_fix_bin.txt", "w");
        file_sub=$fopen("C:\\Users\\32172\\Desktop\\fft_fix\\scr\\valid_adder\\sub_fix_bin.txt", "w");

        #(T + 1) rstn = 1; 
        #(T - 1) ;
        repeat(512)
            begin
                a=a_mem[i];
                b=b_mem[i];
                vld_in=1;
                #(T);
                vld_in=0;
                if(vld_out)
                    $fdisplay(file_adder,"%b",r);
                #(T);
                vld_in=1;
                b=~b_mem[i]+1'b1;
                #(T);
                vld_in=0;
                if(vld_out)
                    $fdisplay(file_sub,"%b",r);
                #(T);    
                i=i+1;
            end
        $fclose(file_adder);
        $fclose(file_sub);

        $finish;
    end
initial begin
   $dumpfile("fix_adder_tb.vcd"); //生成的vcd文件名称
   $dumpvars(0, fix_adder_tb); //tb模块名称
end
endmodule

fix_adder_tb.vcd
$date
	Wed Feb 12 23:46:24 2025
$end
$version
	Icarus Verilog
$end
$timescale
	1s
$end
$scope module fix_adder_tb $end
$var wire 1 ! vld_out $end
$var wire 16 " r [15:0] $end
$var wire 1 # overflow $end
$var reg 16 $ a [15:0] $end
$var reg 16 % b [15:0] $end
$var reg 1 & clk $end
$var reg 1 ' rstn $end
$var reg 1 ( vld_in $end
$var integer 32 ) file_adder [31:0] $end
$var integer 32 * file_sub [31:0] $end
$var integer 32 + i [31:0] $end
$scope module fix_adder_u1N $end
$var wire 16 , a [15:0] $end
$var wire 16 - b [15:0] $end
$var wire 1 & clk $end
$var wire 1 # overflow $end
$var wire 1 ' rstn $end
$var wire 1 ( vld_in $end
$var wire 1 ! vld_out $end
$var wire 16 . r [15:0] $end
$var reg 17 / a_reg [16:0] $end
$var reg 1 0 a_sign $end
$var reg 17 1 b_reg [16:0] $end
$var reg 1 2 b_sign $end
$var reg 17 3 c [16:0] $end
$var reg 1 4 finish_add $end
$var reg 1 5 overflow_reg $end
$var reg 17 6 r_reg [16:0] $end
$var reg 17 7 result_reg [16:0] $end
$var reg 1 8 vld_in_diff $end
$var reg 1 9 vld_out_reg $end
$var integer 32 : i [31:0] $end
$upscope $end
$upscope $end
$enddefinitions $end
#0
$dumpvars
bx :
x9
x8
b0 7
b0 6
05
04
b0 3
02
b0 1
00
b0 /
b0 .
b0 -
b0 ,
b0 +
b10000000000000000000000000000100 *
b10000000000000000000000000000011 )
0(
0'
0&
b0 %
b0 $
0#
b0 "
x!
$end
#5
08
1&
#10
0&
#11
0!
09
1'
#15
1&
#20
0&
1(
b1010001111001 %
b1010001111001 -
b11011111010100 $
b11011111010100 ,
#25
b100110001001101 "
b100110001001101 .
b100110001001101 7
1!
19
14
b11011111110000 3
b100110001001101 6
b10001 :
18
b1010001111001 1
b11011111010100 /
1&
#30
0&
0(
#35
b0 "
b0 .
0!
09
b0 7
04
b0 6
b0 3
08
1&
#40
0&
b1110101110000111 %
b1110101110000111 -
1(
#45
b10001101011011 "
b10001101011011 .
b10001101011011 7
1!
19
14
b11111111110000100 3
b10001101011011 6
b10001 :
18
12
b11110101110000111 1
1&
#50
0&
0(
#55
b0 "
b0 .
0!
09
b0 7
04
b0 6
b0 3
08
1&
#60
0&
1(
b1110000001001101 %
b1110000001001101 -
b1100011011010110 $
b1100011011010110 ,
b1 +
#65
b1010011100100011 "
b1010011100100011 .
b11010011100100011 7
1!
19
14
b11100000011011100 3
b11010011100100011 6
b10001 :
18
10
b11110000001001101 1
b11100011011010110 /
1&
#70
0&
0(
#75
b0 "
b0 .
0!
09
b0 7
04
b0 6
b0 3
08
1&
#80
0&
b1111110110011 %
b1111110110011 -
1(
#85
b1110011010001001 "
b1110011010001001 .
b11110011010001001 7
1!
19
14
b1111111110110 3
b11110011010001001 6
b10001 :
18
02
b1111110110011 1
1&
#90
0&
0(
#95
b0 "
b0 .
0!
09
b0 7
04
b0 6
b0 3
08
1&
#100
0&
1(
b1111010101011 %
b1111010101011 -
b1100111110001 $
b1100111110001 ,
b10 +
#105
b11100010011100 "
b11100010011100 .
b11100010011100 7
1!
19
14
b11100010011100 6
b1111111100011 3
b10001 :
18
00
b1111010101011 1
b1100111110001 /
1&
#110
0&
0(
#115
b0 "
b0 .
0!
09
b0 7
04
b0 6
b0 3
08
1&
#120
0&
b1110000101010101 %
b1110000101010101 -
1(
#125
b1111101101000110 "
b1111101101000110 .
b11111101101000110 7
1!
19
14
b11111101101000110 6
b111110001 3
b10001 :
18
12
b11110000101010101 1
1&
#130
0&
0(
#135
b0 "
b0 .
0!
09
b0 7
04
b0 6
b0 3
08
1&
#140
0&
1(
b1110010110001101 %
b1110010110001101 -
b10010100110011 $
b10010100110011 ,
b11 +
#145
b101011000000 "
b101011000000 .
b101011000000 7
1!
19
14
b101011000000 6
b11110010100111111 3
b10001 :
18
b11110010110001101 1
b10010100110011 /
1&
#150
0&
0(
#155
b0 "
b0 .
0!
09
b0 7
04
b0 6
b0 3
08
1&
#160
0&
b1101001110011 %
b1101001110011 -
1(
#165
b11111110100110 "
b11111110100110 .
b11111110100110 7
1!
19
14
b11111110100110 6
b1110011 3
b10001 :
18
02
b1101001110011 1
1&
#170
0&
0(
#175
b0 "
b0 .
0!
09
b0 7
04
b0 6
b0 3
08
1&
#180
0&
1(
b11100000111 %
b11100000111 -
b11100100111100 $
b11100100111100 ,
b100 +
#185
b100000001000011 "
b100000001000011 .
b100000001000011 7
1!
19
14
b11111100111100 3
b100000001000011 6
b10001 :
18
b11100000111 1
b11100100111100 /
1&
#190
0&
0(
#195
b0 "
b0 .
0!
09
b0 7
04
b0 6
b0 3
08
1&
#200
0&
b1111100011111001 %
b1111100011111001 -
1(
#205
b11001000110101 "
b11001000110101 .
b11001000110101 7
1!
19
14
b11111100111111000 3
b11001000110101 6
b10001 :
18
12
b11111100011111001 1
1&
#210
0&
0(
#215
b0 "
b0 .
0!
09
b0 7
04
b0 6
b0 3
08
1&
#220
0&
1(
b10101001000001 %
b10101001000001 -
b1100001100011101 $
b1100001100011101 ,
b101 +
#225
b1110110101011110 "
b1110110101011110 .
b11110110101011110 7
1!
19
14
b11110110101011110 6
b1000000001 3
b10001 :
18
02
10
b10101001000001 1
b11100001100011101 /
1&
#230
0&
0(
#235
b0 "
b0 .
0!
09
b0 7
04
b0 6
b0 3
08
1&
#240
0&
b1101010110111111 %
b1101010110111111 -
1(
#245
b1001100011011100 "
b1001100011011100 .
b11001100011011100 7
1!
19
14
b11001100011011100 6
b11100011100111111 3
b10001 :
18
12
b11101010110111111 1
1&
#250
0&
0(
#255
b0 "
b0 .
0!
09
b0 7
04
b0 6
b0 3
08
1&
#260
0&
1(
b10001001101100 %
b10001001101100 -
b1110101100111001 $
b1110101100111001 ,
b110 +
#265
b110110100101 "
b110110100101 .
b110110100101 7
1!
19
14
b11110001001111000 3
b110110100101 6
b10001 :
18
02
b10001001101100 1
b11110101100111001 /
1&
#270
0&
0(
#275
b0 "
b0 .
0!
09
b0 7
04
b0 6
b0 3
08
1&
#280
0&
b1101110110010100 %
b1101110110010100 -
1(
#285
b1100100011001101 "
b1100100011001101 .
b11100100011001101 7
1!
19
14
b11111111100110000 3
b11100100011001101 6
b10001 :
18
12
b11101110110010100 1
1&
#290
0&
0(
#295
b0 "
b0 .
0!
09
b0 7
04
b0 6
b0 3
08
1&
#300
0&
1(
b1110000001110110 %
b1110000001110110 -
b10000100000010 $
b10000100000010 ,
b111 +
#305
b101111000 "
b101111000 .
b101111000 7
1!
19
14
b101111000 6
b11110000000000110 3
b10001 :
18
00
b11110000001110110 1
b10000100000010 /
1&
#310
0&
0(
#315
b0 "
b0 .
0!
09
b0 7
04
b0 6
b0 3
08
1&
#320
0&
b1111110001010 %
b1111110001010 -
1(
#325
b100000010001100 "
b100000010001100 .
b100000010001100 7
1!
19
14
b100000010001100 6
b11111100000010 3
b10001 :
18
02
b1111110001010 1
1&
#330
0&
0(
#335
b0 "
b0 .
0!
09
b0 7
04
b0 6
b0 3
08
1&
#340
0&
1(
b1100100100001101 %
b1100100100001101 -
b10011100001000 $
b10011100001000 ,
b1000 +
#345
b1111000000010101 "
b1111000000010101 .
b11111000000010101 7
1!
19
14
b111100001000 3
b11111000000010101 6
b10001 :
18
12
b11100100100001101 1
b10011100001000 /
1&
#350
0&
0(
#355
b0 "
b0 .
0!
09
b0 7
04
b0 6
b0 3
08
1&
#360
0&
b11011011110011 %
b11011011110011 -
1(
#365
b101110111111011 "
b101110111111011 .
b101110111111011 7
1!
19
14
b10011000000000 3
b101110111111011 6
b10001 :
18
02
b11011011110011 1
1&
#370
0&
0(
#375
b0 "
b0 .
0!
09
b0 7
04
b0 6
b0 3
08
1&
#380
0&
1(
b10011010110110 %
b10011010110110 -
b1111101000110100 $
b1111101000110100 ,
b1001 +
#385
b10000011101010 "
b10000011101010 .
b10000011101010 7
1!
19
14
b11111111000110100 3
b10000011101010 6
b10001 :
18
10
b10011010110110 1
b11111101000110100 /
1&
#390
0&
0(
#395
b0 "
b0 .
0!
09
b0 7
04
b0 6
b0 3
08
1&
#400
0&
b1101100101001010 %
b1101100101001010 -
1(
#405
b1101001101111110 "
b1101001101111110 .
b11101001101111110 7
1!
19
14
b11111100000000000 3
b11101001101111110 6
b10001 :
18
12
b11101100101001010 1
1&
#410
0&
0(
#415
b0 "
b0 .
0!
09
b0 7
04
b0 6
b0 3
08
1&
#420
0&
1(
b11101111010011 %
b11101111010011 -
b1110000110011011 $
b1110000110011011 ,
b1010 +
#425
b1110101101110 "
b1110101101110 .
b1110101101110 7
1!
19
14
b1110101101110 6
b11110001110010011 3
b10001 :
18
02
b11101111010011 1
b11110000110011011 /
1&
#430
0&
0(
#435
b0 "
b0 .
0!
09
b0 7
04
b0 6
b0 3
08
1&
#440
0&
b1100010000101101 %
b1100010000101101 -
1(
#445
b1010010111001000 "
b1010010111001000 .
b11010010111001000 7
1!
19
14
b11010010111001000 6
b11100000000111111 3
b10001 :
18
12
b11100010000101101 1
1&
#450
0&
0(
#455
b0 "
b0 .
0!
09
b0 7
04
b0 6
b0 3
08
1&
#460
0&
1(
b1000110101000 %
b1000110101000 -
b1100011100111000 $
b1100011100111000 ,
b1011 +
#465
b1101100011100000 "
b1101100011100000 .
b11101100011100000 7
1!
19
14
b11101100011100000 6
b11100111000 3
b10001 :
18
02
b1000110101000 1
b11100011100111000 /
1&
#470
0&
0(
#475
b0 "
b0 .
0!
09
b0 7
04
b0 6
b0 3
08
1&
#480
0&
b1110111001011000 %
b1110111001011000 -
1(
#485
b1011010110010000 "
b1011010110010000 .
b11011010110010000 7
1!
19
14
b11011010110010000 6
b11100111001111000 3
b10001 :
18
12
b11110111001011000 1
1&
#490
0&
0(
#495
b0 "
b0 .
0!
09
b0 7
04
b0 6
b0 3
08
1&
#500
0&
1(
b1110001011101001 %
b1110001011101001 -
b10110100110001 $
b10110100110001 ,
b1100 +
#505
b1000000011010 "
b1000000011010 .
b1000000011010 7
1!
19
14
b1000000011010 6
b11110111111100001 3
b10001 :
18
00
b11110001011101001 1
b10110100110001 /
1&
#510
0&
0(
#515
b0 "
b0 .
0!
09
b0 7
04
b0 6
b0 3
08
1&
#520
0&
b1110100010111 %
b1110100010111 -
1(
#525
b100101001001000 "
b100101001001000 .
b100101001001000 7
1!
19
14
b100101001001000 6
b11110100110111 3
b10001 :
18
02
b1110100010111 1
1&
#530
0&
0(
#535
b0 "
b0 .
0!
09
b0 7
04
b0 6
b0 3
08
1&
#540
0&
1(
b10001001111110 %
b10001001111110 -
b10011011000111 $
b10011011000111 ,
b1101 +
#545
b100100101000101 "
b100100101000101 .
b100100101000101 7
1!
19
14
b10011011111110 3
b100100101000101 6
b10001 :
18
b10001001111110 1
b10011011000111 /
1&
#550
0&
0(
#555
b0 "
b0 .
0!
09
b0 7
04
b0 6
b0 3
08
1&
#560
0&
b1101110110000010 %
b1101110110000010 -
1(
#565
b10001001001 "
b10001001001 .
b10001001001 7
1!
19
14
b11111111110000110 3
b10001001001 6
b10001 :
18
12
b11101110110000010 1
1&
#570
0&
0(
#575
b0 "
b0 .
0!
09
b0 7
04
b0 6
b0 3
08
1&
#580
0&
1(
b1111100101111100 %
b1111100101111100 -
b10010111101 $
b10010111101 ,
b1110 +
#585
b1111111000111001 "
b1111111000111001 .
b11111111000111001 7
1!
19
14
b111111100 3
b11111111000111001 6
b10001 :
18
b11111100101111100 1
b10010111101 /
1&
#590
0&
0(
#595
b0 "
b0 .
0!
09
b0 7
04
b0 6
b0 3
08
1&
#600
0&
b11010000100 %
b11010000100 -
1(
#605
b101101000001 "
b101101000001 .
b101101000001 7
1!
19
14
b10010111100 3
b101101000001 6
b10001 :
18
02
b11010000100 1
1&
#610
0&
0(
#615
b0 "
b0 .
0!
09
b0 7
04
b0 6
b0 3
08
1&
#620
0&
1(
b1110110001100111 %
b1110110001100111 -
b1100111111110110 $
b1100111111110110 ,
b1111 +
#625
b1011110001011101 "
b1011110001011101 .
b11011110001011101 7
1!
19
14
b11100111111100110 3
b11011110001011101 6
b10001 :
18
12
10
b11110110001100111 1
b11100111111110110 /
1&
#630
0&
0(
#635
b0 "
b0 .
0!
09
b0 7
04
b0 6
b0 3
08
1&
#640
0&
b1001110011001 %
b1001110011001 -
1(
#645
b1110001110001111 "
b1110001110001111 .
b11110001110001111 7
1!
19
14
b1111111110000 3
b11110001110001111 6
b10001 :
18
02
b1001110011001 1
1&
#650
0&
0(
#655
b0 "
b0 .
0!
09
b0 7
04
b0 6
b0 3
08
1&
#660
0&
1(
b10011110111011 %
b10011110111011 -
b1111010001101110 $
b1111010001101110 ,
b10000 +
#665
b1110000101001 "
b1110000101001 .
b1110000101001 7
1!
19
14
b11110011111111110 3
b1110000101001 6
b10001 :
18
b10011110111011 1
b11111010001101110 /
1&
#670
0&
0(
#675
b0 "
b0 .
0!
09
b0 7
04
b0 6
b0 3
08
1&
#680
0&
b1101100001000101 %
b1101100001000101 -
1(
#685
b1100110010110011 "
b1100110010110011 .
b11100110010110011 7
1!
19
14
b11111000001001100 3
b11100110010110011 6
b10001 :
18
12
b11101100001000101 1
1&
#690
0&
0(
#695
b0 "
b0 .
0!
09
b0 7
04
b0 6
b0 3
08
1&
#700
0&
1(
b10110100000101 %
b10110100000101 -
b101110111101 $
b101110111101 ,
b10001 +
#705
b11100011000010 "
b11100011000010 .
b11100011000010 7
1!
19
14
b11100011000010 6
b111100111101 3
b10001 :
18
02
00
b10110100000101 1
b101110111101 /
1&
#710
0&
0(
#715
b0 "
b0 .
0!
09
b0 7
04
b0 6
b0 3
08
1&
#720
0&
b1101001011111011 %
b1101001011111011 -
1(
#725
b1101111010111000 "
b1101111010111000 .
b11101111010111000 7
1!
19
14
b11101111010111000 6
b1111111111 3
b10001 :
18
12
b11101001011111011 1
1&
#730
0&
0(
#735
b0 "
b0 .
0!
09
b0 7
04
b0 6
b0 3
08
1&
#740
0&
1(
b101000011111 %
b101000011111 -
b1100100101011001 $
b1100100101011001 ,
b10010 +
#745
b1101001101111000 "
b1101001101111000 .
b11101001101111000 7
1!
19
14
b11101001101111000 6
b100000011111 3
b10001 :
18
02
10
b101000011111 1
b11100100101011001 /
1&
#750
0&
0(
#755
b0 "
b0 .
0!
09
b0 7
04
b0 6
b0 3
08
1&
#760
0&
b1111010111100001 %
b1111010111100001 -
1(
#765
b1011111100111010 "
b1011111100111010 .
b11011111100111010 7
1!
19
14
b11011111100111010 6
b11100000111000001 3
b10001 :
18
12
b11111010111100001 1
1&
#770
0&
0(
#775
b0 "
b0 .
0!
09
b0 7
04
b0 6
b0 3
08
1&
#780
0&
1(
b11011000000101 %
b11011000000101 -
b1100000101001 $
b1100000101001 ,
b10011 +
#785
b100111000101110 "
b100111000101110 .
b100111000101110 7
1!
19
14
b100111000101110 6
b11000000000001 3
b10001 :
18
02
00
b11011000000101 1
b1100000101001 /
1&
#790
0&
0(
#795
b0 "
b0 .
0!
09
b0 7
04
b0 6
b0 3
08
1&
#800
0&
b1100100111111011 %
b1100100111111011 -
1(
#805
b1110001000100100 "
b1110001000100100 .
b11110001000100100 7
1!
19
14
b11110001000100100 6
b1100111111011 3
b10001 :
18
12
b11100100111111011 1
1&
#810
0&
0(
#815
b0 "
b0 .
0!
09
b0 7
04
b0 6
b0 3
08
1&
#820
0&
1(
b11010010110010 %
b11010010110010 -
b1101110100010110 $
b1101110100010110 ,
b10100 +
#825
b1000111001000 "
b1000111001000 .
b1000111001000 7
1!
19
14
b1000111001000 6
b11111110000110110 3
b10001 :
18
02
10
b11010010110010 1
b11101110100010110 /
1&
#830
0&
0(
#835
b0 "
b0 .
0!
09
b0 7
04
b0 6
b0 3
08
1&
#840
0&
b1100101101001110 %
b1100101101001110 -
1(
#845
b1010100001100100 "
b1010100001100100 .
b11010100001100100 7
1!
19
14
b11010100001100100 6
b11101111100011110 3
b10001 :
18
12
b11100101101001110 1
1&
#850
0&
0(
#855
b0 "
b0 .
0!
09
b0 7
04
b0 6
b0 3
08
1&
#860
0&
1(
b111110011101 %
b111110011101 -
b11111001111111 $
b11111001111111 ,
b10101 +
#865
b100111000011100 "
b100111000011100 .
b100111000011100 7
1!
19
14
b100111000011100 6
b11111111111111 3
b10001 :
18
02
00
b111110011101 1
b11111001111111 /
1&
#870
0&
0(
#875
b0 "
b0 .
0!
09
b0 7
04
b0 6
b0 3
08
1&
#880
0&
b1111000001100011 %
b1111000001100011 -
1(
#885
b10111011100010 "
b10111011100010 .
b10111011100010 7
1!
19
14
b10111011100010 6
b11111000001111111 3
b10001 :
18
12
b11111000001100011 1
1&
#890
0&
0(
#895
b0 "
b0 .
0!
09
b0 7
04
b0 6
b0 3
08
1&
#900
0&
1(
b1101111101001101 %
b1101111101001101 -
b101001110111 $
b101001110111 ,
b10110 +
#905
b1110100111000100 "
b1110100111000100 .
b11110100111000100 7
1!
19
14
b11110100111000100 6
b1111001111111 3
b10001 :
18
b11101111101001101 1
b101001110111 /
1&
#910
0&
0(
#915
b0 "
b0 .
0!
09
b0 7
04
b0 6
b0 3
08
1&
#920
0&
b10000010110011 %
b10000010110011 -
1(
#925
b10101100101010 "
b10101100101010 .
b10101100101010 7
1!
19
14
b10101100101010 6
b11110111 3
b10001 :
18
02
b10000010110011 1
1&
#930
0&
0(
#935
b0 "
b0 .
0!
09
b0 7
04
b0 6
b0 3
08
1&
#940
0&
1(
b1001100100 %
b1001100100 -
b1000000000111 $
b1000000000111 ,
b10111 +
#945
b1001001101011 "
b1001001101011 .
b1001001101011 7
1!
19
14
b100 3
b1001001101011 6
b10001 :
18
b1001100100 1
b1000000000111 /
1&
#950
0&
0(
#955
b0 "
b0 .
0!
09
b0 7
04
b0 6
b0 3
08
1&
#960
0&
b1111110110011100 %
b1111110110011100 -
1(
#965
b110110100011 "
b110110100011 .
b110110100011 7
1!
19
14
b11111000000011100 3
b110110100011 6
b10001 :
18
12
b11111110110011100 1
1&
#970
0&
0(
#975
b0 "
b0 .
0!
09
b0 7
04
b0 6
b0 3
08
1&
#980
0&
1(
b1010001110 %
b1010001110 -
b1100001011000 $
b1100001011000 ,
b11000 +
#985
b1101011100110 "
b1101011100110 .
b1101011100110 7
1!
19
14
b11000 3
b1101011100110 6
b10001 :
18
02
b1010001110 1
b1100001011000 /
1&
#990
0&
0(
#995
b0 "
b0 .
0!
09
b0 7
04
b0 6
b0 3
08
1&
#1000
0&
b1111110101110010 %
b1111110101110010 -
1(
#1005
b1010111001010 "
b1010111001010 .
b1010111001010 7
1!
19
14
b11111100001110000 3
b1010111001010 6
b10001 :
18
12
b11111110101110010 1
1&
#1010
0&
0(
#1015
b0 "
b0 .
0!
09
b0 7
04
b0 6
b0 3
08
1&
#1020
0&
1(
b1101101100111110 %
b1101101100111110 -
b1111101101111011 $
b1111101101111011 ,
b11001 +
#1025
b1101011010111001 "
b1101011010111001 .
b11101011010111001 7
1!
19
14
b11111101101111110 3
b11101011010111001 6
b10001 :
18
10
b11101101100111110 1
b11111101101111011 /
1&
#1030
0&
0(
#1035
b0 "
b0 .
0!
09
b0 7
04
b0 6
b0 3
08
1&
#1040
0&
b10010011000010 %
b10010011000010 -
1(
#1045
b10000000111101 "
b10000000111101 .
b10000000111101 7
1!
19
14
b11111111111000010 3
b10000000111101 6
b10001 :
18
02
b10010011000010 1
1&
#1050
0&
0(
#1055
b0 "
b0 .
0!
09
b0 7
04
b0 6
b0 3
08
1&
#1060
0&
1(
b1100101110010101 %
b1100101110010101 -
b1111011100000100 $
b1111011100000100 ,
b11010 +
#1065
b1100001010011001 "
b1100001010011001 .
b11100001010011001 7
1!
19
14
b11111111100000100 3
b11100001010011001 6
b10001 :
18
12
b11100101110010101 1
b11111011100000100 /
1&
#1070
0&
0(
#1075
b0 "
b0 .
0!
09
b0 7
04
b0 6
b0 3
08
1&
#1080
0&
b11010001101011 %
b11010001101011 -
1(
#1085
b10101101101111 "
b10101101101111 .
b10101101101111 7
1!
19
14
b11111010000000000 3
b10101101101111 6
b10001 :
18
02
b11010001101011 1
1&
#1090
0&
0(
#1095
b0 "
b0 .
0!
09
b0 7
04
b0 6
b0 3
08
1&
#1100
0&
1(
b1111111111010 %
b1111111111010 -
b1111111001101 $
b1111111001101 ,
b11011 +
#1105
b11111111000111 "
b11111111000111 .
b11111111000111 7
1!
19
14
b1111111111000 3
b11111111000111 6
b10001 :
18
00
b1111111111010 1
b1111111001101 /
1&
#1110
0&
0(
#1115
b0 "
b0 .
0!
09
b0 7
04
b0 6
b0 3
08
1&
#1120
0&
b1110000000000110 %
b1110000000000110 -
1(
#1125
b1111111111010011 "
b1111111111010011 .
b11111111111010011 7
1!
19
14
b1100 3
b11111111111010011 6
b10001 :
18
12
b11110000000000110 1
1&
#1130
0&
0(
#1135
b0 "
b0 .
0!
09
b0 7
04
b0 6
b0 3
08
1&
#1140
0&
1(
b1100101100101111 %
b1100101100101111 -
b1110010010100010 $
b1110010010100010 ,
b11100 +
#1145
b1010111111010001 "
b1010111111010001 .
b11010111111010001 7
1!
19
14
b11100000000101110 3
b11010111111010001 6
b10001 :
18
10
b11100101100101111 1
b11110010010100010 /
1&
#1150
0&
0(
#1155
b0 "
b0 .
0!
09
b0 7
04
b0 6
b0 3
08
1&
#1160
0&
b11010011010001 %
b11010011010001 -
1(
#1165
b1100101110011 "
b1100101110011 .
b1100101110011 7
1!
19
14
b11110010010000000 3
b1100101110011 6
b10001 :
18
02
b11010011010001 1
1&
#1170
0&
0(
#1175
b0 "
b0 .
0!
09
b0 7
04
b0 6
b0 3
08
1&
#1180
0&
1(
b11000100111 %
b11000100111 -
b1111111110010001 $
b1111111110010001 ,
b11101 +
#1185
b10110111000 "
b10110111000 .
b10110111000 7
1!
19
14
b10110111000 6
b11111111000000111 3
b10001 :
18
b11000100111 1
b11111111110010001 /
1&
#1190
0&
0(
#1195
b0 "
b0 .
0!
09
b0 7
04
b0 6
b0 3
08
1&
#1200
0&
b1111100111011001 %
b1111100111011001 -
1(
#1205
b1111100101101010 "
b1111100101101010 .
b11111100101101010 7
1!
19
14
b11111100101101010 6
b11111111110010001 3
b10001 :
18
12
b11111100111011001 1
1&
#1210
0&
0(
#1215
b0 "
b0 .
0!
09
b0 7
04
b0 6
b0 3
08
1&
#1220
0&
1(
b10111010110011 %
b10111010110011 -
b110000001010 $
b110000001010 ,
b11110 +
#1225
b11101010111101 "
b11101010111101 .
b11101010111101 7
1!
19
14
b110000000010 3
b11101010111101 6
b10001 :
18
02
00
b10111010110011 1
b110000001010 /
1&
#1230
0&
0(
#1235
b0 "
b0 .
0!
09
b0 7
04
b0 6
b0 3
08
1&
#1240
0&
b1101000101001101 %
b1101000101001101 -
1(
#1245
b1101110101010111 "
b1101110101010111 .
b11101110101010111 7
1!
19
14
b1000 3
b11101110101010111 6
b10001 :
18
12
b11101000101001101 1
1&
#1250
0&
0(
#1255
b0 "
b0 .
0!
09
b0 7
04
b0 6
b0 3
08
1&
#1260
0&
1(
b10110101110011 %
b10110101110011 -
b1101101111100100 $
b1101101111100100 ,
b11111 +
#1265
b100101010111 "
b100101010111 .
b100101010111 7
1!
19
14
b11111111111100000 3
b100101010111 6
b10001 :
18
02
10
b10110101110011 1
b11101101111100100 /
1&
#1270
0&
0(
#1275
b0 "
b0 .
0!
09
b0 7
04
b0 6
b0 3
08
1&
#1280
0&
b1101001010001101 %
b1101001010001101 -
1(
#1285
b1010111001110001 "
b1010111001110001 .
b11010111001110001 7
1!
19
14
b11101001110001100 3
b11010111001110001 6
b10001 :
18
12
b11101001010001101 1
1&
#1290
0&
0(
#1295
b0 "
b0 .
0!
09
b0 7
04
b0 6
b0 3
08
1&
#1300
0&
1(
b1100101000101000 %
b1100101000101000 -
b1111111010011 $
b1111111010011 ,
b100000 +
#1305
b1110100111111011 "
b1110100111111011 .
b11110100111111011 7
1!
19
14
b1111000000000 3
b11110100111111011 6
b10001 :
18
00
b11100101000101000 1
b1111111010011 /
1&
#1310
0&
0(
#1315
b0 "
b0 .
0!
09
b0 7
04
b0 6
b0 3
08
1&
#1320
0&
b11010111011000 %
b11010111011000 -
1(
#1325
b101010110101011 "
b101010110101011 .
b101010110101011 7
1!
19
14
b11111111010000 3
b101010110101011 6
b10001 :
18
02
b11010111011000 1
1&
#1330
0&
0(
#1335
b0 "
b0 .
0!
09
b0 7
04
b0 6
b0 3
08
1&
#1340
0&
1(
b111110110111 %
b111110110111 -
b1111001000110100 $
b1111001000110100 ,
b100001 +
#1345
b111101011 "
b111101011 .
b111101011 7
1!
19
14
b11111111000110100 3
b111101011 6
b10001 :
18
10
b111110110111 1
b11111001000110100 /
1&
#1350
0&
0(
#1355
b0 "
b0 .
0!
09
b0 7
04
b0 6
b0 3
08
1&
#1360
0&
b1111000001001001 %
b1111000001001001 -
1(
#1365
b1110001001111101 "
b1110001001111101 .
b11110001001111101 7
1!
19
14
b11111000000000000 3
b11110001001111101 6
b10001 :
18
12
b11111000001001001 1
1&
#1370
0&
0(
